{
  "type": "service_account",
  "project_id": "-----GET FROM FIREBASE CONSOLE-----",
  "private_key_id": "-----GET FROM FIREBASE CONSOLE-----",
  "private_key": "-----GET FROM FIREBASE CONSOLE-----",
  "client_email": "-----GET FROM FIREBASE CONSOLE-----",
  "client_id": "-----GET FROM FIREBASE CONSOLE-----",
  "auth_uri": "-----GET FROM FIREBASE CONSOLE-----",
  "token_uri": "-----GET FROM FIREBASE CONSOLE-----",
  "auth_provider_x509_cert_url": "-----GET FROM FIREBASE CONSOLE-----",
  "client_x509_cert_url": "-----GET FROM FIREBASE CONSOLE-----"
}
